kafka_connect_watcher/__init__.py
kafka_connect_watcher/aws_emf.py
kafka_connect_watcher/aws_sns/__init__.py
kafka_connect_watcher/aws_sns/default.j2
kafka_connect_watcher/aws_sns/email.j2
kafka_connect_watcher/aws_sns/sms.j2
kafka_connect_watcher/cli.py
kafka_connect_watcher/cluster.py
kafka_connect_watcher/config.py
kafka_connect_watcher/connectors_eval.py
kafka_connect_watcher/error_rules.py
kafka_connect_watcher/logger.py
kafka_connect_watcher/notifications.py
kafka_connect_watcher/threads_settings.py
kafka_connect_watcher/tools.py
kafka_connect_watcher/watcher-config.spec.json
kafka_connect_watcher/watcher.py
kafka_connect_watcher-0.6.0.dist-info/LICENSE
kafka_connect_watcher-0.6.0.dist-info/METADATA
kafka_connect_watcher-0.6.0.dist-info/WHEEL
kafka_connect_watcher-0.6.0.dist-info/entry_points.txt
kafka_connect_watcher-0.6.0.dist-info/RECORD
